[
  {
    "category": "Task info",
    "label": "Info field 'name' % missing",
    "value": 0,
    "severity": 0,
    "severity_value": 0,
    "condition": "pct_missing <= 0",
    "message": "Task info field 'name' should be defined\n  Task: predict_modality\n  Field: name\n  Percentage missing: 0"
  },
  {
    "category": "Task info",
    "label": "Info field 'label' % missing",
    "value": 0,
    "severity": 0,
    "severity_value": 0,
    "condition": "pct_missing <= 0",
    "message": "Task info field 'label' should be defined\n  Task: predict_modality\n  Field: label\n  Percentage missing: 0"
  },
  {
    "category": "Task info",
    "label": "Info field 'summary' % missing",
    "value": 0,
    "severity": 0,
    "severity_value": 0,
    "condition": "pct_missing <= 0",
    "message": "Task info field 'summary' should be defined\n  Task: predict_modality\n  Field: summary\n  Percentage missing: 0"
  },
  {
    "category": "Task info",
    "label": "Info field 'description' % missing",
    "value": 0,
    "severity": 0,
    "severity_value": 0,
    "condition": "pct_missing <= 0",
    "message": "Task info field 'description' should be defined\n  Task: predict_modality\n  Field: description\n  Percentage missing: 0"
  },
  {
    "category": "Dataset info",
    "label": "Info field 'name' % missing",
    "value": 0,
    "severity": 0,
    "severity_value": 0,
    "condition": "pct_missing <= 0",
    "message": "Dataset info field 'name' should be defined\n  Task: predict_modality\n  Field: name\n  Percentage missing: 0"
  },
  {
    "category": "Dataset info",
    "label": "Info field 'label' % missing",
    "value": 0,
    "severity": 0,
    "severity_value": 0,
    "condition": "pct_missing <= 0",
    "message": "Dataset info field 'label' should be defined\n  Task: predict_modality\n  Field: label\n  Percentage missing: 0"
  },
  {
    "category": "Dataset info",
    "label": "Info field 'summary' % missing",
    "value": 0,
    "severity": 0,
    "severity_value": 0,
    "condition": "pct_missing <= 0",
    "message": "Dataset info field 'summary' should be defined\n  Task: predict_modality\n  Field: summary\n  Percentage missing: 0"
  },
  {
    "category": "Dataset info",
    "label": "Info field 'description' % missing",
    "value": 0,
    "severity": 0,
    "severity_value": 0,
    "condition": "pct_missing <= 0",
    "message": "Dataset info field 'description' should be defined\n  Task: predict_modality\n  Field: description\n  Percentage missing: 0"
  },
  {
    "category": "Dataset info",
    "label": "Info field 'references' % missing",
    "value": 0,
    "severity": 0,
    "severity_value": 0,
    "condition": "pct_missing <= 0",
    "message": "Dataset info field 'references' should be defined\n  Task: predict_modality\n  Field: references\n  Percentage missing: 0"
  },
  {
    "category": "Method info",
    "label": "Info field 'name' % missing",
    "value": 0,
    "severity": 0,
    "severity_value": 0,
    "condition": "pct_missing <= 0",
    "message": "Method info field 'name' should be defined\n  Task: predict_modality\n  Field: name\n  Percentage missing: 0"
  },
  {
    "category": "Method info",
    "label": "Info field 'label' % missing",
    "value": 0,
    "severity": 0,
    "severity_value": 0,
    "condition": "pct_missing <= 0",
    "message": "Method info field 'label' should be defined\n  Task: predict_modality\n  Field: label\n  Percentage missing: 0"
  },
  {
    "category": "Method info",
    "label": "Info field 'commit' % missing",
    "value": 0,
    "severity": 0,
    "severity_value": 0,
    "condition": "pct_missing <= 0",
    "message": "Method info field 'commit' should be defined\n  Task: predict_modality\n  Field: commit\n  Percentage missing: 0"
  },
  {
    "category": "Method info",
    "label": "Info field 'summary' % missing",
    "value": 0,
    "severity": 0,
    "severity_value": 0,
    "condition": "pct_missing <= 0",
    "message": "Method info field 'summary' should be defined\n  Task: predict_modality\n  Field: summary\n  Percentage missing: 0"
  },
  {
    "category": "Method info",
    "label": "Info field 'description' % missing",
    "value": 0,
    "severity": 0,
    "severity_value": 0,
    "condition": "pct_missing <= 0",
    "message": "Method info field 'description' should be defined\n  Task: predict_modality\n  Field: description\n  Percentage missing: 0"
  },
  {
    "category": "Method info",
    "label": "Info field 'references' % missing",
    "value": 0.6,
    "severity": 3,
    "severity_value": 3,
    "condition": "pct_missing <= 0",
    "message": "Method info field 'references' should be defined\n  Task: predict_modality\n  Field: references\n  Percentage missing: 60"
  },
  {
    "category": "Metric info",
    "label": "Info field 'name' % missing",
    "value": 0,
    "severity": 0,
    "severity_value": 0,
    "condition": "pct_missing <= 0",
    "message": "Metric info field 'name' should be defined\n  Task: predict_modality\n  Field: name\n  Percentage missing: 0"
  },
  {
    "category": "Metric info",
    "label": "Info field 'label' % missing",
    "value": 0,
    "severity": 0,
    "severity_value": 0,
    "condition": "pct_missing <= 0",
    "message": "Metric info field 'label' should be defined\n  Task: predict_modality\n  Field: label\n  Percentage missing: 0"
  },
  {
    "category": "Metric info",
    "label": "Info field 'commit' % missing",
    "value": 0,
    "severity": 0,
    "severity_value": 0,
    "condition": "pct_missing <= 0",
    "message": "Metric info field 'commit' should be defined\n  Task: predict_modality\n  Field: commit\n  Percentage missing: 0"
  },
  {
    "category": "Metric info",
    "label": "Info field 'summary' % missing",
    "value": 0,
    "severity": 0,
    "severity_value": 0,
    "condition": "pct_missing <= 0",
    "message": "Metric info field 'summary' should be defined\n  Task: predict_modality\n  Field: summary\n  Percentage missing: 0"
  },
  {
    "category": "Metric info",
    "label": "Info field 'description' % missing",
    "value": 0,
    "severity": 0,
    "severity_value": 0,
    "condition": "pct_missing <= 0",
    "message": "Metric info field 'description' should be defined\n  Task: predict_modality\n  Field: description\n  Percentage missing: 0"
  },
  {
    "category": "Metric info",
    "label": "Info field 'references' % missing",
    "value": 1,
    "severity": 3,
    "severity_value": 3,
    "condition": "pct_missing <= 0",
    "message": "Metric info field 'references' should be defined\n  Task: predict_modality\n  Field: references\n  Percentage missing: 100"
  },
  {
    "category": "Raw results",
    "label": "Task number of results",
    "value": 16,
    "severity": 3,
    "severity_value": 9.5,
    "condition": "length(dataset_info) * length(results) == length(method_info) * length(metric_info)",
    "message": "Number of results should be equal to #datasets × #methods × #metrics \n  Task: predict_modality\n  Number of results: 16\n  Number of datasets: 4\n  Number of methods: 10\n  Number of metrics: 8\n  Expected number of results: 320\n"
  },
  {
    "category": "Raw results",
    "label": "Dataset 'openproblems_neurips2021/bmmc_multiome/normal' % missing",
    "value": 0.9,
    "severity": 3,
    "severity_value": 9,
    "condition": "pct_missing <= 0.1",
    "message": "Percentage of missing results should be less than 10%\n  Task: predict_modality\n  Dataset: openproblems_neurips2021/bmmc_multiome/normal\n  Number of results: 8\n  Expected number of results: 80\n  Percentage missing: 90%\n"
  },
  {
    "category": "Raw results",
    "label": "Dataset 'openproblems_neurips2021/bmmc_cite/normal' % missing",
    "value": 1,
    "severity": 3,
    "severity_value": 10,
    "condition": "pct_missing <= 0.1",
    "message": "Percentage of missing results should be less than 10%\n  Task: predict_modality\n  Dataset: openproblems_neurips2021/bmmc_cite/normal\n  Number of results: 0\n  Expected number of results: 80\n  Percentage missing: 100%\n"
  },
  {
    "category": "Raw results",
    "label": "Dataset 'openproblems_neurips2021/bmmc_cite/swap' % missing",
    "value": 0.9,
    "severity": 3,
    "severity_value": 9,
    "condition": "pct_missing <= 0.1",
    "message": "Percentage of missing results should be less than 10%\n  Task: predict_modality\n  Dataset: openproblems_neurips2021/bmmc_cite/swap\n  Number of results: 8\n  Expected number of results: 80\n  Percentage missing: 90%\n"
  },
  {
    "category": "Raw results",
    "label": "Dataset 'openproblems_neurips2021/bmmc_multiome/swap' % missing",
    "value": 1,
    "severity": 3,
    "severity_value": 10,
    "condition": "pct_missing <= 0.1",
    "message": "Percentage of missing results should be less than 10%\n  Task: predict_modality\n  Dataset: openproblems_neurips2021/bmmc_multiome/swap\n  Number of results: 0\n  Expected number of results: 80\n  Percentage missing: 100%\n"
  },
  {
    "category": "Raw results",
    "label": "Method 'mean_per_gene' % missing",
    "value": 1,
    "severity": 3,
    "severity_value": 10,
    "condition": "pct_missing <= 0.1",
    "message": "Percentage of missing results should be less than 10%\n  Task: predict_modality\n  Method: mean_per_gene\n  Number of results: 0\n  Expected number of results: 32\n  Percentage missing: 100%\n"
  },
  {
    "category": "Raw results",
    "label": "Method 'random_predict' % missing",
    "value": 1,
    "severity": 3,
    "severity_value": 10,
    "condition": "pct_missing <= 0.1",
    "message": "Percentage of missing results should be less than 10%\n  Task: predict_modality\n  Method: random_predict\n  Number of results: 0\n  Expected number of results: 32\n  Percentage missing: 100%\n"
  },
  {
    "category": "Raw results",
    "label": "Method 'zeros' % missing",
    "value": 1,
    "severity": 3,
    "severity_value": 10,
    "condition": "pct_missing <= 0.1",
    "message": "Percentage of missing results should be less than 10%\n  Task: predict_modality\n  Method: zeros\n  Number of results: 0\n  Expected number of results: 32\n  Percentage missing: 100%\n"
  },
  {
    "category": "Raw results",
    "label": "Method 'solution' % missing",
    "value": 1,
    "severity": 3,
    "severity_value": 10,
    "condition": "pct_missing <= 0.1",
    "message": "Percentage of missing results should be less than 10%\n  Task: predict_modality\n  Method: solution\n  Number of results: 0\n  Expected number of results: 32\n  Percentage missing: 100%\n"
  },
  {
    "category": "Raw results",
    "label": "Method 'knnr_py' % missing",
    "value": 1,
    "severity": 3,
    "severity_value": 10,
    "condition": "pct_missing <= 0.1",
    "message": "Percentage of missing results should be less than 10%\n  Task: predict_modality\n  Method: knnr_py\n  Number of results: 0\n  Expected number of results: 32\n  Percentage missing: 100%\n"
  },
  {
    "category": "Raw results",
    "label": "Method 'knnr_r' % missing",
    "value": 1,
    "severity": 3,
    "severity_value": 10,
    "condition": "pct_missing <= 0.1",
    "message": "Percentage of missing results should be less than 10%\n  Task: predict_modality\n  Method: knnr_r\n  Number of results: 0\n  Expected number of results: 32\n  Percentage missing: 100%\n"
  },
  {
    "category": "Raw results",
    "label": "Method 'lm' % missing",
    "value": 1,
    "severity": 3,
    "severity_value": 10,
    "condition": "pct_missing <= 0.1",
    "message": "Percentage of missing results should be less than 10%\n  Task: predict_modality\n  Method: lm\n  Number of results: 0\n  Expected number of results: 32\n  Percentage missing: 100%\n"
  },
  {
    "category": "Raw results",
    "label": "Method 'newwave_knnr' % missing",
    "value": 0.5,
    "severity": 3,
    "severity_value": 5,
    "condition": "pct_missing <= 0.1",
    "message": "Percentage of missing results should be less than 10%\n  Task: predict_modality\n  Method: newwave_knnr\n  Number of results: 16\n  Expected number of results: 32\n  Percentage missing: 50%\n"
  },
  {
    "category": "Raw results",
    "label": "Method 'random_forest' % missing",
    "value": 1,
    "severity": 3,
    "severity_value": 10,
    "condition": "pct_missing <= 0.1",
    "message": "Percentage of missing results should be less than 10%\n  Task: predict_modality\n  Method: random_forest\n  Number of results: 0\n  Expected number of results: 32\n  Percentage missing: 100%\n"
  },
  {
    "category": "Raw results",
    "label": "Method 'guanlab_dengkw_pm' % missing",
    "value": 1,
    "severity": 3,
    "severity_value": 10,
    "condition": "pct_missing <= 0.1",
    "message": "Percentage of missing results should be less than 10%\n  Task: predict_modality\n  Method: guanlab_dengkw_pm\n  Number of results: 0\n  Expected number of results: 32\n  Percentage missing: 100%\n"
  },
  {
    "category": "Raw results",
    "label": "Metric 'mean_pearson_per_cell' % missing",
    "value": 0.95,
    "severity": 3,
    "severity_value": 9.5,
    "condition": "pct_missing <= 0.1",
    "message": "Percentage of missing results should be less than 10%\n  Task: predict_modality\n  Metric: mean_pearson_per_cell\n  Number of results: 2\n  Expected number of results: 40\n  Percentage missing: 95%\n"
  },
  {
    "category": "Raw results",
    "label": "Metric 'mean_spearman_per_cell' % missing",
    "value": 0.95,
    "severity": 3,
    "severity_value": 9.5,
    "condition": "pct_missing <= 0.1",
    "message": "Percentage of missing results should be less than 10%\n  Task: predict_modality\n  Metric: mean_spearman_per_cell\n  Number of results: 2\n  Expected number of results: 40\n  Percentage missing: 95%\n"
  },
  {
    "category": "Raw results",
    "label": "Metric 'mean_pearson_per_gene' % missing",
    "value": 0.95,
    "severity": 3,
    "severity_value": 9.5,
    "condition": "pct_missing <= 0.1",
    "message": "Percentage of missing results should be less than 10%\n  Task: predict_modality\n  Metric: mean_pearson_per_gene\n  Number of results: 2\n  Expected number of results: 40\n  Percentage missing: 95%\n"
  },
  {
    "category": "Raw results",
    "label": "Metric 'mean_spearman_per_gene' % missing",
    "value": 0.95,
    "severity": 3,
    "severity_value": 9.5,
    "condition": "pct_missing <= 0.1",
    "message": "Percentage of missing results should be less than 10%\n  Task: predict_modality\n  Metric: mean_spearman_per_gene\n  Number of results: 2\n  Expected number of results: 40\n  Percentage missing: 95%\n"
  },
  {
    "category": "Raw results",
    "label": "Metric 'overall_pearson' % missing",
    "value": 0.95,
    "severity": 3,
    "severity_value": 9.5,
    "condition": "pct_missing <= 0.1",
    "message": "Percentage of missing results should be less than 10%\n  Task: predict_modality\n  Metric: overall_pearson\n  Number of results: 2\n  Expected number of results: 40\n  Percentage missing: 95%\n"
  },
  {
    "category": "Raw results",
    "label": "Metric 'overall_spearman' % missing",
    "value": 0.95,
    "severity": 3,
    "severity_value": 9.5,
    "condition": "pct_missing <= 0.1",
    "message": "Percentage of missing results should be less than 10%\n  Task: predict_modality\n  Metric: overall_spearman\n  Number of results: 2\n  Expected number of results: 40\n  Percentage missing: 95%\n"
  },
  {
    "category": "Raw results",
    "label": "Metric 'rmse' % missing",
    "value": 0.95,
    "severity": 3,
    "severity_value": 9.5,
    "condition": "pct_missing <= 0.1",
    "message": "Percentage of missing results should be less than 10%\n  Task: predict_modality\n  Metric: rmse\n  Number of results: 2\n  Expected number of results: 40\n  Percentage missing: 95%\n"
  },
  {
    "category": "Raw results",
    "label": "Metric 'mae' % missing",
    "value": 0.95,
    "severity": 3,
    "severity_value": 9.5,
    "condition": "pct_missing <= 0.1",
    "message": "Percentage of missing results should be less than 10%\n  Task: predict_modality\n  Metric: mae\n  Number of results: 2\n  Expected number of results: 40\n  Percentage missing: 95%\n"
  },
  {
    "category": "Raw results",
    "label": "Task number of successful processes",
    "value": 6,
    "severity": 2,
    "severity_value": 2.5,
    "condition": "sum(results$succeeded) + sum(metric_component_results$succeeded) == nrow(results) + nrow(metric_component_results)",
    "message": "Number of successful processes should be equal to the number of attempted processes\n  Task: predict_modality\n  Succeeded processes: 6\n  Attempted processes: 8\n  Percentage failed: 25%\n"
  },
  {
    "category": "Raw results",
    "label": "Dataset 'openproblems_neurips2021/bmmc_multiome/normal' % failed",
    "value": 0,
    "severity": 0,
    "severity_value": 0,
    "condition": "pct_failed <= 0.1",
    "message": "Percentage of failed processes should be less than 10%\n  Task: predict_modality\n  Dataset: openproblems_neurips2021/bmmc_multiome/normal\n  Succeeded processes: 1\n  Attempted processes: 1\n  Percentage failed: 0%\n"
  },
  {
    "category": "Raw results",
    "label": "Dataset 'openproblems_neurips2021/bmmc_cite/normal' % failed",
    "value": 1,
    "severity": 3,
    "severity_value": 10,
    "condition": "pct_failed <= 0.1",
    "message": "Percentage of failed processes should be less than 10%\n  Task: predict_modality\n  Dataset: openproblems_neurips2021/bmmc_cite/normal\n  Succeeded processes: 0\n  Attempted processes: 1\n  Percentage failed: 100%\n"
  },
  {
    "category": "Raw results",
    "label": "Dataset 'openproblems_neurips2021/bmmc_cite/swap' % failed",
    "value": 0,
    "severity": 0,
    "severity_value": 0,
    "condition": "pct_failed <= 0.1",
    "message": "Percentage of failed processes should be less than 10%\n  Task: predict_modality\n  Dataset: openproblems_neurips2021/bmmc_cite/swap\n  Succeeded processes: 1\n  Attempted processes: 1\n  Percentage failed: 0%\n"
  },
  {
    "category": "Raw results",
    "label": "Dataset 'openproblems_neurips2021/bmmc_multiome/swap' % failed",
    "value": 1,
    "severity": 3,
    "severity_value": 10,
    "condition": "pct_failed <= 0.1",
    "message": "Percentage of failed processes should be less than 10%\n  Task: predict_modality\n  Dataset: openproblems_neurips2021/bmmc_multiome/swap\n  Succeeded processes: 0\n  Attempted processes: 1\n  Percentage failed: 100%\n"
  },
  {
    "category": "Raw results",
    "label": "Method 'mean_per_gene' % failed",
    "value": -1,
    "severity": 3,
    "severity_value": -1,
    "condition": "pct_failed <= 0.1",
    "message": "Percentage of failed processes should be less than 10%\n  Task: predict_modality\n  Method: mean_per_gene\n  Succeeded processes: 0\n  Attempted processes: 0\n  Percentage failed: NaN%\n"
  },
  {
    "category": "Raw results",
    "label": "Method 'random_predict' % failed",
    "value": -1,
    "severity": 3,
    "severity_value": -1,
    "condition": "pct_failed <= 0.1",
    "message": "Percentage of failed processes should be less than 10%\n  Task: predict_modality\n  Method: random_predict\n  Succeeded processes: 0\n  Attempted processes: 0\n  Percentage failed: NaN%\n"
  },
  {
    "category": "Raw results",
    "label": "Method 'zeros' % failed",
    "value": -1,
    "severity": 3,
    "severity_value": -1,
    "condition": "pct_failed <= 0.1",
    "message": "Percentage of failed processes should be less than 10%\n  Task: predict_modality\n  Method: zeros\n  Succeeded processes: 0\n  Attempted processes: 0\n  Percentage failed: NaN%\n"
  },
  {
    "category": "Raw results",
    "label": "Method 'solution' % failed",
    "value": -1,
    "severity": 3,
    "severity_value": -1,
    "condition": "pct_failed <= 0.1",
    "message": "Percentage of failed processes should be less than 10%\n  Task: predict_modality\n  Method: solution\n  Succeeded processes: 0\n  Attempted processes: 0\n  Percentage failed: NaN%\n"
  },
  {
    "category": "Raw results",
    "label": "Method 'knnr_py' % failed",
    "value": -1,
    "severity": 3,
    "severity_value": -1,
    "condition": "pct_failed <= 0.1",
    "message": "Percentage of failed processes should be less than 10%\n  Task: predict_modality\n  Method: knnr_py\n  Succeeded processes: 0\n  Attempted processes: 0\n  Percentage failed: NaN%\n"
  },
  {
    "category": "Raw results",
    "label": "Method 'knnr_r' % failed",
    "value": -1,
    "severity": 3,
    "severity_value": -1,
    "condition": "pct_failed <= 0.1",
    "message": "Percentage of failed processes should be less than 10%\n  Task: predict_modality\n  Method: knnr_r\n  Succeeded processes: 0\n  Attempted processes: 0\n  Percentage failed: NaN%\n"
  },
  {
    "category": "Raw results",
    "label": "Method 'lm' % failed",
    "value": -1,
    "severity": 3,
    "severity_value": -1,
    "condition": "pct_failed <= 0.1",
    "message": "Percentage of failed processes should be less than 10%\n  Task: predict_modality\n  Method: lm\n  Succeeded processes: 0\n  Attempted processes: 0\n  Percentage failed: NaN%\n"
  },
  {
    "category": "Raw results",
    "label": "Method 'newwave_knnr' % failed",
    "value": 0.5,
    "severity": 3,
    "severity_value": 5,
    "condition": "pct_failed <= 0.1",
    "message": "Percentage of failed processes should be less than 10%\n  Task: predict_modality\n  Method: newwave_knnr\n  Succeeded processes: 2\n  Attempted processes: 4\n  Percentage failed: 50%\n"
  },
  {
    "category": "Raw results",
    "label": "Method 'random_forest' % failed",
    "value": -1,
    "severity": 3,
    "severity_value": -1,
    "condition": "pct_failed <= 0.1",
    "message": "Percentage of failed processes should be less than 10%\n  Task: predict_modality\n  Method: random_forest\n  Succeeded processes: 0\n  Attempted processes: 0\n  Percentage failed: NaN%\n"
  },
  {
    "category": "Raw results",
    "label": "Method 'guanlab_dengkw_pm' % failed",
    "value": -1,
    "severity": 3,
    "severity_value": -1,
    "condition": "pct_failed <= 0.1",
    "message": "Percentage of failed processes should be less than 10%\n  Task: predict_modality\n  Method: guanlab_dengkw_pm\n  Succeeded processes: 0\n  Attempted processes: 0\n  Percentage failed: NaN%\n"
  },
  {
    "category": "Raw results",
    "label": "Metric component 'correlation' % failed",
    "value": 0,
    "severity": 0,
    "severity_value": 0,
    "condition": "pct_failed <= 0.1",
    "message": "Percentage of failed processes should be less than 10%\n  Task: predict_modality\n  Metric component: correlation\n  Succeeded processes: 2\n  Attempted processes: 2\n  Percentage failed: 0%\n"
  },
  {
    "category": "Raw results",
    "label": "Metric component 'mse' % failed",
    "value": 0,
    "severity": 0,
    "severity_value": 0,
    "condition": "pct_failed <= 0.1",
    "message": "Percentage of failed processes should be less than 10%\n  Task: predict_modality\n  Metric component: mse\n  Succeeded processes: 2\n  Attempted processes: 2\n  Percentage failed: 0%\n"
  },
  {
    "category": "Raw results",
    "label": "Dataset `openproblems_neurips2021/bmmc_multiome/normal' number of control methods",
    "value": 0,
    "severity": 3,
    "severity_value": 3,
    "condition": "n_controls != length(control_methods)",
    "message": "Number of successful control methods for a dataset should equal the number of controls\n  Task: predict_modality\n  Dataset: openproblems_neurips2021/bmmc_multiome/normal\n  Succeeded control_methods: 0\n  Total control methods: 4\n  Percentage succeeded: 0%\n"
  },
  {
    "category": "Raw results",
    "label": "Dataset `openproblems_neurips2021/bmmc_cite/normal' number of control methods",
    "value": 0,
    "severity": 3,
    "severity_value": 3,
    "condition": "n_controls != length(control_methods)",
    "message": "Number of successful control methods for a dataset should equal the number of controls\n  Task: predict_modality\n  Dataset: openproblems_neurips2021/bmmc_cite/normal\n  Succeeded control_methods: 0\n  Total control methods: 4\n  Percentage succeeded: 0%\n"
  },
  {
    "category": "Raw results",
    "label": "Dataset `openproblems_neurips2021/bmmc_cite/swap' number of control methods",
    "value": 0,
    "severity": 3,
    "severity_value": 3,
    "condition": "n_controls != length(control_methods)",
    "message": "Number of successful control methods for a dataset should equal the number of controls\n  Task: predict_modality\n  Dataset: openproblems_neurips2021/bmmc_cite/swap\n  Succeeded control_methods: 0\n  Total control methods: 4\n  Percentage succeeded: 0%\n"
  },
  {
    "category": "Raw results",
    "label": "Dataset `openproblems_neurips2021/bmmc_multiome/swap' number of control methods",
    "value": 0,
    "severity": 3,
    "severity_value": 3,
    "condition": "n_controls != length(control_methods)",
    "message": "Number of successful control methods for a dataset should equal the number of controls\n  Task: predict_modality\n  Dataset: openproblems_neurips2021/bmmc_multiome/swap\n  Succeeded control_methods: 0\n  Total control methods: 4\n  Percentage succeeded: 0%\n"
  },
  {
    "category": "Raw results",
    "label": "Metric 'mean_pearson_per_cell' number of control methods",
    "value": 0,
    "severity": 3,
    "severity_value": 3,
    "condition": "n_controls != length(datasets) * length(control_methods)",
    "message": "Number of metric scores for control methods should be equal to #datasets × #control_methods\n  Task: predict_modality\n  Metric: mean_pearson_per_cell\n  Control method scores: 0\n  Expected control method scores: 16\n  Percentage succeeded: 0%\n"
  },
  {
    "category": "Raw results",
    "label": "Metric 'mean_spearman_per_cell' number of control methods",
    "value": 0,
    "severity": 3,
    "severity_value": 3,
    "condition": "n_controls != length(datasets) * length(control_methods)",
    "message": "Number of metric scores for control methods should be equal to #datasets × #control_methods\n  Task: predict_modality\n  Metric: mean_spearman_per_cell\n  Control method scores: 0\n  Expected control method scores: 16\n  Percentage succeeded: 0%\n"
  },
  {
    "category": "Raw results",
    "label": "Metric 'mean_pearson_per_gene' number of control methods",
    "value": 0,
    "severity": 3,
    "severity_value": 3,
    "condition": "n_controls != length(datasets) * length(control_methods)",
    "message": "Number of metric scores for control methods should be equal to #datasets × #control_methods\n  Task: predict_modality\n  Metric: mean_pearson_per_gene\n  Control method scores: 0\n  Expected control method scores: 16\n  Percentage succeeded: 0%\n"
  },
  {
    "category": "Raw results",
    "label": "Metric 'mean_spearman_per_gene' number of control methods",
    "value": 0,
    "severity": 3,
    "severity_value": 3,
    "condition": "n_controls != length(datasets) * length(control_methods)",
    "message": "Number of metric scores for control methods should be equal to #datasets × #control_methods\n  Task: predict_modality\n  Metric: mean_spearman_per_gene\n  Control method scores: 0\n  Expected control method scores: 16\n  Percentage succeeded: 0%\n"
  },
  {
    "category": "Raw results",
    "label": "Metric 'overall_pearson' number of control methods",
    "value": 0,
    "severity": 3,
    "severity_value": 3,
    "condition": "n_controls != length(datasets) * length(control_methods)",
    "message": "Number of metric scores for control methods should be equal to #datasets × #control_methods\n  Task: predict_modality\n  Metric: overall_pearson\n  Control method scores: 0\n  Expected control method scores: 16\n  Percentage succeeded: 0%\n"
  },
  {
    "category": "Raw results",
    "label": "Metric 'overall_spearman' number of control methods",
    "value": 0,
    "severity": 3,
    "severity_value": 3,
    "condition": "n_controls != length(datasets) * length(control_methods)",
    "message": "Number of metric scores for control methods should be equal to #datasets × #control_methods\n  Task: predict_modality\n  Metric: overall_spearman\n  Control method scores: 0\n  Expected control method scores: 16\n  Percentage succeeded: 0%\n"
  },
  {
    "category": "Raw results",
    "label": "Metric 'rmse' number of control methods",
    "value": 0,
    "severity": 3,
    "severity_value": 3,
    "condition": "n_controls != length(datasets) * length(control_methods)",
    "message": "Number of metric scores for control methods should be equal to #datasets × #control_methods\n  Task: predict_modality\n  Metric: rmse\n  Control method scores: 0\n  Expected control method scores: 16\n  Percentage succeeded: 0%\n"
  },
  {
    "category": "Raw results",
    "label": "Metric 'mae' number of control methods",
    "value": 0,
    "severity": 3,
    "severity_value": 3,
    "condition": "n_controls != length(datasets) * length(control_methods)",
    "message": "Number of metric scores for control methods should be equal to #datasets × #control_methods\n  Task: predict_modality\n  Metric: mae\n  Control method scores: 0\n  Expected control method scores: 16\n  Percentage succeeded: 0%\n"
  }
]
